potaru/__init__.py
potaru/__main__.py
potaru/client.py
potaru-0.4.0.dist-info/entry_points.txt
potaru-0.4.0.dist-info/WHEEL
potaru-0.4.0.dist-info/METADATA
potaru-0.4.0.dist-info/RECORD
