Metadata-Version: 2.1
Name: potaru
Version: 0.4.0
Summary: 
Author: Alon Gubkin
Author-email: alon.gubkin@gmail.com
Requires-Python: >=3.6,<4.0
Classifier: Programming Language :: Python :: 3
Classifier: Programming Language :: Python :: 3.6
Classifier: Programming Language :: Python :: 3.7
Classifier: Programming Language :: Python :: 3.8
Classifier: Programming Language :: Python :: 3.9
Requires-Dist: click (>=8.0.1,<9.0.0)
Requires-Dist: requests (>=2.25.1,<3.0.0)
